locust/__init__.py
locust/cli.py
locust/git.py
locust/git_pb2.py
locust/parse.py
locust/parse_pb2.py
locust/render.py
locust/render_pb2.py
locust/version.py
locust/ci_helpers/__init__.py
locust/ci_helpers/github.py
tests/__init__.py
tests/config.py
tests/test_git.py
tests/test_parse.py
tests/test_render.py
bugout_locust-0.3.2.dist-info/LICENSE
bugout_locust-0.3.2.dist-info/METADATA
bugout_locust-0.3.2.dist-info/WHEEL
bugout_locust-0.3.2.dist-info/entry_points.txt
bugout_locust-0.3.2.dist-info/top_level.txt
bugout_locust-0.3.2.dist-info/RECORD
