Metadata-Version: 2.1
Name: bugout-locust
Version: 0.3.2
Summary: Locust: Track changes to Python code across git refs
Home-page: https://github.com/simiotics/locust
Author: Neeraj Kashyap
Author-email: neeraj@bugout.dev
Classifier: Development Status :: 2 - Pre-Alpha
Classifier: Programming Language :: Python
License-File: LICENSE
Requires-Dist: pygit2
Requires-Dist: PyYAML
Requires-Dist: lxml
Requires-Dist: pydantic
Requires-Dist: protobuf (==3.20.0)
Requires-Dist: requests
Provides-Extra: dev
Requires-Dist: black ; extra == 'dev'
Requires-Dist: mypy ; extra == 'dev'
Requires-Dist: wheel ; extra == 'dev'
Requires-Dist: mypy-protobuf ; extra == 'dev'
Requires-Dist: types-PyYAML ; extra == 'dev'
Requires-Dist: types-requests ; extra == 'dev'
Provides-Extra: distribute
Requires-Dist: twine ; extra == 'distribute'
